Workbook

Sheet Cover
B2: Progress Technologies
B3: Risk-Driven Statement of Applicability - ISO/IEC 27001:2022 (Working Workbook)
B5: Document ID | C5: PT-ISMS-SOA-001
B6: Version / status | C6: 1.0 - Draft for management approval
B7: Date | C7: 46321
B8: Author | C8: Devavrat Yadav
B9: Original author | C9: Taimuri Jlal - original project brief, scenario and SoA template (Project 02)
B10: Classification | C10: Confidential
B11: Next review | C11: 46503
B12: Companion document | C12: Word report: Progress Technologies - Risk-Driven Statement of Applicability (sections 1-22)
B15: Sheets
B16: Summary | C16: Control counts by theme and status (live formulas from the SoA sheet)
B17: SoA | C17: All 93 Annex A controls: applicability, status, justification, evidence, linked risks, validation flag
B18: Exclusions | C18: 10 excluded controls with reason, alternative measure and re-evaluation trigger
B19: Risk Register | C19: R-001 to R-013 with inherent and target residual ratings
B20: Traceability | C20: Control-by-risk grid with live coverage counts
B21: Evidence Index | C21: EV-01 to EV-50 with owner, system of record, cadence and live count of controls citing each
B22: Actions | C22: Priority remediation plan A-01 to A-20
B23: Additional Controls | C23: Controls beyond Annex A (clause 6.1.3 b)
B25: Important
B26: Statuses, owners and evidence artefacts are the author's assessed baseline derived from the scenario. They are not confirmed records.
B27: Never keep a control as Implemented unless its evidence can be produced on demand. Use the 'Evidence validated' column on the SoA sheet; any Implemented control not marked Yes is flagged.
B28: Yellow cells on the SoA sheet (owner, evidence validated) are for Progress Technologies to complete.
B29: Applicable, Status and Evidence validated are drop-down lists; Summary and Traceability counts recalculate when they change.

Sheet Summary
A1: Statement of Applicability Summary
A2: Live counts from the SoA sheet. Baseline at 26 October 2026.
A4: Theme | B4: Total | C4: Applicable | D4: Excluded | E4: Implemented | F4: Partial | G4: Planned
A5: 5. Organizational | B5: =COUNTIFS(SoA!$A$2:$A$94,$A5) -> 37 | C5: =COUNTIFS(SoA!$A$2:$A$94,$A5,SoA!$D$2:$D$94,"Yes") -> 37 | D5: =COUNTIFS(SoA!$A$2:$A$94,$A5,SoA!$D$2:$D$94,"No") -> 0 | E5: =COUNTIFS(SoA!$A$2:$A$94,$A5,SoA!$E$2:$E$94,"Implemented") -> 11 | F5: =COUNTIFS(SoA!$A$2:$A$94,$A5,SoA!$E$2:$E$94,"Partial") -> 23 | G5: =COUNTIFS(SoA!$A$2:$A$94,$A5,SoA!$E$2:$E$94,"Planned") -> 3
A6: 6. People | B6: =COUNTIFS(SoA!$A$2:$A$94,$A6) -> 8 | C6: =COUNTIFS(SoA!$A$2:$A$94,$A6,SoA!$D$2:$D$94,"Yes") -> 8 | D6: =COUNTIFS(SoA!$A$2:$A$94,$A6,SoA!$D$2:$D$94,"No") -> 0 | E6: =COUNTIFS(SoA!$A$2:$A$94,$A6,SoA!$E$2:$E$94,"Implemented") -> 6 | F6: =COUNTIFS(SoA!$A$2:$A$94,$A6,SoA!$E$2:$E$94,"Partial") -> 2 | G6: =COUNTIFS(SoA!$A$2:$A$94,$A6,SoA!$E$2:$E$94,"Planned") -> 0
A7: 7. Physical | B7: =COUNTIFS(SoA!$A$2:$A$94,$A7) -> 14 | C7: =COUNTIFS(SoA!$A$2:$A$94,$A7,SoA!$D$2:$D$94,"Yes") -> 5 | D7: =COUNTIFS(SoA!$A$2:$A$94,$A7,SoA!$D$2:$D$94,"No") -> 9 | E7: =COUNTIFS(SoA!$A$2:$A$94,$A7,SoA!$E$2:$E$94,"Implemented") -> 1 | F7: =COUNTIFS(SoA!$A$2:$A$94,$A7,SoA!$E$2:$E$94,"Partial") -> 4 | G7: =COUNTIFS(SoA!$A$2:$A$94,$A7,SoA!$E$2:$E$94,"Planned") -> 0
A8: 8. Technological | B8: =COUNTIFS(SoA!$A$2:$A$94,$A8) -> 34 | C8: =COUNTIFS(SoA!$A$2:$A$94,$A8,SoA!$D$2:$D$94,"Yes") -> 33 | D8: =COUNTIFS(SoA!$A$2:$A$94,$A8,SoA!$D$2:$D$94,"No") -> 1 | E8: =COUNTIFS(SoA!$A$2:$A$94,$A8,SoA!$E$2:$E$94,"Implemented") -> 15 | F8: =COUNTIFS(SoA!$A$2:$A$94,$A8,SoA!$E$2:$E$94,"Partial") -> 13 | G8: =COUNTIFS(SoA!$A$2:$A$94,$A8,SoA!$E$2:$E$94,"Planned") -> 5
A9: TOTAL | B9: =SUM(B5:B8) -> 93 | C9: =SUM(C5:C8) -> 83 | D9: =SUM(D5:D8) -> 10 | E9: =SUM(E5:E8) -> 33 | F9: =SUM(F5:F8) -> 42 | G9: =SUM(G5:G8) -> 8
A11: Integrity checks
A12: Total controls = 93 | B12: =IF(B9=93,"OK","CHECK") -> OK
A13: Applicable + excluded = total | B13: =IF(C9+D9=B9,"OK","CHECK") -> OK
A14: Implemented + partial + planned = applicable | B14: =IF(E9+F9+G9=C9,"OK","CHECK") -> OK
A15: Implemented controls with evidence not yet validated | B15: =COUNTIF(SoA!$M$2:$M$94,"Validate evidence") -> 33
A16: Rows with status conflict | B16: =COUNTIF(SoA!$M$2:$M$94,"Status conflict") -> 0
A18: Share of applicable controls
A19: Implemented | B19: =IF($C$9=0,0,E9/$C$9) -> 0.39759036
A20: Partial | B20: =IF($C$9=0,0,F9/$C$9) -> 0.5060241
A21: Planned | B21: =IF($C$9=0,0,G9/$C$9) -> 0.096385542
A23: Note: Implemented status is a baseline assumption pending the evidence walk-through (see Cover sheet).

Sheet SoA
A1: Theme | B1: Ref | C1: Control | D1: Applicable | E1: Status | F1: Justification (risk link) | G1: Evidence Ref | H1: Linked risks | I1: Exclusion ref | J1: Remediation action | K1: Control owner | L1: Evidence validated | M1: Check
A2: 5. Organizational | B2: 5.1 | C2: Policies for information security | D2: Yes | E2: Implemented | F2: Governance anchor of the ISMS (clause 5.2); direction for treating R-001 and R-003; customer contracts require a documented policy set. | G2: EV-01 | H2: R-001, R-003 | L2: Pending | M2: =IF(AND(E2="Implemented",L2<>"Yes"),"Validate evidence",IF(AND(D2="Yes",E2="N/A"),"Status conflict",IF(AND(D2="No",E2<>"N/A"),"Status conflict","OK"))) -> Validate evidence
A3: 5. Organizational | B3: 5.2 | C3: Information security roles and responsibilities | D3: Yes | E3: Implemented | F3: Names accountable owners for ISMS, risk and cloud security in a fully remote organisation (R-001, R-003, R-004). | G3: EV-03 | H3: R-003, R-004 | L3: Pending | M3: =IF(AND(E3="Implemented",L3<>"Yes"),"Validate evidence",IF(AND(D3="Yes",E3="N/A"),"Status conflict",IF(AND(D3="No",E3<>"N/A"),"Status conflict","OK"))) -> Validate evidence
A4: 5. Organizational | B4: 5.3 | C4: Segregation of duties | D4: Yes | E4: Partial | F4: Limits single-person misuse of production and admin rights (R-001, R-003, R-004). Peer-approved deployments operate; break-glass and small-team admin overlap need compensating review. | G4: EV-11, EV-27 | H4: R-001, R-003, R-004 | L4: n/a | M4: =IF(AND(E4="Implemented",L4<>"Yes"),"Validate evidence",IF(AND(D4="Yes",E4="N/A"),"Status conflict",IF(AND(D4="No",E4<>"N/A"),"Status conflict","OK"))) -> OK
A5: 5. Organizational | B5: 5.4 | C5: Management responsibilities | D5: Yes | E5: Implemented | F5: Management directs and enforces compliance across a remote workforce (R-004, R-007). | G5: EV-03, EV-04 | H5: R-004, R-007 | L5: Pending | M5: =IF(AND(E5="Implemented",L5<>"Yes"),"Validate evidence",IF(AND(D5="Yes",E5="N/A"),"Status conflict",IF(AND(D5="No",E5<>"N/A"),"Status conflict","OK"))) -> Validate evidence
A6: 5. Organizational | B6: 5.5 | C6: Contact with authorities | D6: Yes | E6: Partial | F6: Needed for GDPR breach notification and incident escalation (R-001, R-011). Contact list exists; escalation paths untested. | G6: EV-35 | H6: R-011 | L6: n/a | M6: =IF(AND(E6="Implemented",L6<>"Yes"),"Validate evidence",IF(AND(D6="Yes",E6="N/A"),"Status conflict",IF(AND(D6="No",E6<>"N/A"),"Status conflict","OK"))) -> OK
A7: 5. Organizational | B7: 5.6 | C7: Contact with special interest groups | D7: Yes | E7: Partial | F7: Low-cost source of cloud-threat and vulnerability bulletins (R-003, R-007). Memberships to be formalised. | G7: EV-35 | H7: R-007 | L7: n/a | M7: =IF(AND(E7="Implemented",L7<>"Yes"),"Validate evidence",IF(AND(D7="Yes",E7="N/A"),"Status conflict",IF(AND(D7="No",E7<>"N/A"),"Status conflict","OK"))) -> OK
A8: 5. Organizational | B8: 5.7 | C8: Threat intelligence | D8: Yes | E8: Partial | F8: Feeds R-003, R-007 and R-009 from AWS and vendor advisories. Triage SLA and reporting not yet formal. | G8: EV-34 | H8: R-003, R-007, R-009 | L8: n/a | M8: =IF(AND(E8="Implemented",L8<>"Yes"),"Validate evidence",IF(AND(D8="Yes",E8="N/A"),"Status conflict",IF(AND(D8="No",E8<>"N/A"),"Status conflict","OK"))) -> OK
A9: 5. Organizational | B9: 5.8 | C9: Information security in project management | D9: Yes | E9: Partial | F9: Security gate for new features and infrastructure changes (R-003, R-013). Gate not yet mandatory for every project type. | G9: EV-40 | H9: R-003, R-013 | L9: n/a | M9: =IF(AND(E9="Implemented",L9<>"Yes"),"Validate evidence",IF(AND(D9="Yes",E9="N/A"),"Status conflict",IF(AND(D9="No",E9<>"N/A"),"Status conflict","OK"))) -> OK
A10: 5. Organizational | B10: 5.9 | C10: Inventory of information and other associated assets | D10: Yes | E10: Partial | F10: Unknown assets cannot be protected (R-001, R-002, R-003). Laptops tracked in MDM and AWS resources in AWS Config; information asset owners incomplete. | G10: EV-07, EV-24 | H10: R-002 | L10: n/a | M10: =IF(AND(E10="Implemented",L10<>"Yes"),"Validate evidence",IF(AND(D10="Yes",E10="N/A"),"Status conflict",IF(AND(D10="No",E10<>"N/A"),"Status conflict","OK"))) -> OK
A11: 5. Organizational | B11: 5.10 | C11: Acceptable use of information and other associated assets | D11: Yes | E11: Implemented | F11: Sets endpoint, SaaS and data-handling behaviour for remote staff (R-002, R-004, R-007); acknowledged at onboarding. | G11: EV-08 | H11: R-002, R-004, R-007 | L11: Pending | M11: =IF(AND(E11="Implemented",L11<>"Yes"),"Validate evidence",IF(AND(D11="Yes",E11="N/A"),"Status conflict",IF(AND(D11="No",E11<>"N/A"),"Status conflict","OK"))) -> Validate evidence
A12: 5. Organizational | B12: 5.11 | C12: Return of assets | D12: Yes | E12: Implemented | F12: Prevents leavers retaining laptops or data (R-002, R-004). Courier return and reconciliation process used for remote leavers. | G12: EV-20, EV-24 | H12: R-002, R-004 | L12: Pending | M12: =IF(AND(E12="Implemented",L12<>"Yes"),"Validate evidence",IF(AND(D12="Yes",E12="N/A"),"Status conflict",IF(AND(D12="No",E12<>"N/A"),"Status conflict","OK"))) -> Validate evidence
A13: 5. Organizational | B13: 5.12 | C13: Classification of information | D13: Yes | E13: Partial | F13: Drives encryption, access and retention for customer data (R-001, R-011, R-012). Scheme approved; tagging of cloud data stores in progress. | G13: EV-09 | H13: R-001, R-011, R-012 | L13: n/a | M13: =IF(AND(E13="Implemented",L13<>"Yes"),"Validate evidence",IF(AND(D13="Yes",E13="N/A"),"Status conflict",IF(AND(D13="No",E13<>"N/A"),"Status conflict","OK"))) -> OK
A14: 5. Organizational | B14: 5.13 | C14: Labelling of information | D14: Yes | E14: Planned | F14: Proportionate labelling only: document footers and cloud resource tags (R-001, R-011). Automated tagging scheduled in Wave 1. | G14: EV-09 | H14: R-011 | J14: A-07 | L14: n/a | M14: =IF(AND(E14="Implemented",L14<>"Yes"),"Validate evidence",IF(AND(D14="Yes",E14="N/A"),"Status conflict",IF(AND(D14="No",E14<>"N/A"),"Status conflict","OK"))) -> OK
A15: 5. Organizational | B15: 5.14 | C15: Information transfer | D15: Yes | E15: Partial | F15: Controls transfer of customer and internal data via TLS, approved sharing tools and NDAs (R-001, R-011). Customer data export rules being finalised. | G15: EV-09, EV-30 | H15: R-001, R-011 | L15: n/a | M15: =IF(AND(E15="Implemented",L15<>"Yes"),"Validate evidence",IF(AND(D15="Yes",E15="N/A"),"Status conflict",IF(AND(D15="No",E15<>"N/A"),"Status conflict","OK"))) -> OK
A16: 5. Organizational | B16: 5.15 | C16: Access control | D16: Yes | E16: Implemented | F16: Least-privilege, role-based access to AWS and SaaS (R-001, R-004). | G16: EV-10, EV-11 | H16: R-001, R-004 | L16: Pending | M16: =IF(AND(E16="Implemented",L16<>"Yes"),"Validate evidence",IF(AND(D16="Yes",E16="N/A"),"Status conflict",IF(AND(D16="No",E16<>"N/A"),"Status conflict","OK"))) -> Validate evidence
A17: 5. Organizational | B17: 5.16 | C17: Identity management | D17: Yes | E17: Implemented | F17: Central identity provider with joiner-mover-leaver lifecycle (R-001, R-004). | G17: EV-11, EV-46 | H17: R-001, R-004 | L17: Pending | M17: =IF(AND(E17="Implemented",L17<>"Yes"),"Validate evidence",IF(AND(D17="Yes",E17="N/A"),"Status conflict",IF(AND(D17="No",E17<>"N/A"),"Status conflict","OK"))) -> Validate evidence
A18: 5. Organizational | B18: 5.17 | C18: Authentication information | D18: Yes | E18: Implemented | F18: Password manager, MFA and secrets manager for machine credentials (R-001, R-007, R-010). | G18: EV-44, EV-46 | H18: R-001, R-007, R-010 | L18: Pending | M18: =IF(AND(E18="Implemented",L18<>"Yes"),"Validate evidence",IF(AND(D18="Yes",E18="N/A"),"Status conflict",IF(AND(D18="No",E18<>"N/A"),"Status conflict","OK"))) -> Validate evidence
A19: 5. Organizational | B19: 5.18 | C19: Access rights | D19: Yes | E19: Partial | F19: Quarterly AWS access reviews operate; extension to all SaaS applications outstanding (R-001, R-004). | G19: EV-11 | H19: R-001, R-004 | J19: A-09 | L19: n/a | M19: =IF(AND(E19="Implemented",L19<>"Yes"),"Validate evidence",IF(AND(D19="Yes",E19="N/A"),"Status conflict",IF(AND(D19="No",E19<>"N/A"),"Status conflict","OK"))) -> OK
A20: 5. Organizational | B20: 5.19 | C20: Information security in supplier relationships | D20: Yes | E20: Partial | F20: AWS and other suppliers hold customer data or underpin the service (R-005, R-009). Supplier tiering in progress. | G20: EV-12 | H20: R-005, R-009 | L20: n/a | M20: =IF(AND(E20="Implemented",L20<>"Yes"),"Validate evidence",IF(AND(D20="Yes",E20="N/A"),"Status conflict",IF(AND(D20="No",E20<>"N/A"),"Status conflict","OK"))) -> OK
A21: 5. Organizational | B21: 5.20 | C21: Addressing information security within supplier agreements | D21: Yes | E21: Partial | F21: Security and data-protection terms with AWS and sub-processors (R-005, R-011). Customer flow-down clauses under review. | G21: EV-13 | H21: R-005, R-011 | L21: n/a | M21: =IF(AND(E21="Implemented",L21<>"Yes"),"Validate evidence",IF(AND(D21="Yes",E21="N/A"),"Status conflict",IF(AND(D21="No",E21<>"N/A"),"Status conflict","OK"))) -> OK
A22: 5. Organizational | B22: 5.21 | C22: Managing information security in the ICT supply chain | D22: Yes | E22: Partial | F22: Open-source dependencies and CI/CD tooling are the main ICT supply chain (R-009). Dependency scanning live; SBOM and formal standard not yet produced. | G22: EV-12, EV-26 | H22: R-005, R-009 | L22: n/a | M22: =IF(AND(E22="Implemented",L22<>"Yes"),"Validate evidence",IF(AND(D22="Yes",E22="N/A"),"Status conflict",IF(AND(D22="No",E22<>"N/A"),"Status conflict","OK"))) -> OK
A23: 5. Organizational | B23: 5.22 | C23: Monitoring, review and change management of supplier services | D23: Yes | E23: Partial | F23: Ongoing assurance over AWS (R-005) and the evidence base for inherited physical controls. Annual review of AWS certificates and reports being scheduled. | G23: EV-12 | H23: R-005 | J23: A-04 | L23: n/a | M23: =IF(AND(E23="Implemented",L23<>"Yes"),"Validate evidence",IF(AND(D23="Yes",E23="N/A"),"Status conflict",IF(AND(D23="No",E23<>"N/A"),"Status conflict","OK"))) -> OK
A24: 5. Organizational | B24: 5.23 | C24: Information security for use of cloud services | D24: Yes | E24: Implemented | F24: Core control for a 100% AWS company: cloud security standard and shared-responsibility matrix define who secures what (R-003, R-005). | G24: EV-14, EV-31 | H24: R-003, R-005 | L24: Pending | M24: =IF(AND(E24="Implemented",L24<>"Yes"),"Validate evidence",IF(AND(D24="Yes",E24="N/A"),"Status conflict",IF(AND(D24="No",E24<>"N/A"),"Status conflict","OK"))) -> Validate evidence
A25: 5. Organizational | B25: 5.24 | C25: Information security incident management planning and preparation | D25: Yes | E25: Implemented | F25: Defined incident roles, severity model and reporting channels (R-001, R-006). | G25: EV-15 | H25: R-006 | L25: Pending | M25: =IF(AND(E25="Implemented",L25<>"Yes"),"Validate evidence",IF(AND(D25="Yes",E25="N/A"),"Status conflict",IF(AND(D25="No",E25<>"N/A"),"Status conflict","OK"))) -> Validate evidence
A26: 5. Organizational | B26: 5.25 | C26: Assessment and decision on information security events | D26: Yes | E26: Partial | F26: Triage criteria defined; evidence of consistent event classification still thin (R-001, R-003). | G26: EV-15, EV-28 | H26: R-003 | L26: n/a | M26: =IF(AND(E26="Implemented",L26<>"Yes"),"Validate evidence",IF(AND(D26="Yes",E26="N/A"),"Status conflict",IF(AND(D26="No",E26<>"N/A"),"Status conflict","OK"))) -> OK
A27: 5. Organizational | B27: 5.26 | C27: Response to information security incidents | D27: Yes | E27: Partial | F27: Playbooks for cloud credential compromise and data exposure; not yet validated by a tabletop exercise (R-001, R-003, R-006, R-008). | G27: EV-15 | H27: R-003, R-006, R-008 | J27: A-15 | L27: n/a | M27: =IF(AND(E27="Implemented",L27<>"Yes"),"Validate evidence",IF(AND(D27="Yes",E27="N/A"),"Status conflict",IF(AND(D27="No",E27<>"N/A"),"Status conflict","OK"))) -> OK
A28: 5. Organizational | B28: 5.27 | C28: Learning from information security incidents | D28: Yes | E28: Partial | F28: Post-incident review template exists; limited operating history to evidence (R-003, R-006). | G28: EV-15 | H28: R-006 | L28: n/a | M28: =IF(AND(E28="Implemented",L28<>"Yes"),"Validate evidence",IF(AND(D28="Yes",E28="N/A"),"Status conflict",IF(AND(D28="No",E28<>"N/A"),"Status conflict","OK"))) -> OK
A29: 5. Organizational | B29: 5.28 | C29: Collection of evidence | D29: Yes | E29: Planned | F29: Forensic readiness (log retention, snapshot and chain-of-custody procedure) needed for customer and regulator enquiries (R-001, R-004). | G29: EV-15, EV-28 | H29: R-004 | J29: A-08 | L29: n/a | M29: =IF(AND(E29="Implemented",L29<>"Yes"),"Validate evidence",IF(AND(D29="Yes",E29="N/A"),"Status conflict",IF(AND(D29="No",E29<>"N/A"),"Status conflict","OK"))) -> OK
A30: 5. Organizational | B30: 5.29 | C30: Information security during disruption | D30: Yes | E30: Partial | F30: Keeps security controls effective during outage and failover (R-005, R-006, R-008). | G30: EV-16 | H30: R-005, R-006, R-008 | L30: n/a | M30: =IF(AND(E30="Implemented",L30<>"Yes"),"Validate evidence",IF(AND(D30="Yes",E30="N/A"),"Status conflict",IF(AND(D30="No",E30<>"N/A"),"Status conflict","OK"))) -> OK
A31: 5. Organizational | B31: 5.30 | C31: ICT readiness for business continuity | D31: Yes | E31: Partial | F31: Multi-AZ design in place; cross-region recovery test pending (R-005, R-006, R-008). | G31: EV-16, EV-29 | H31: R-005, R-006, R-008 | J31: A-18 | L31: n/a | M31: =IF(AND(E31="Implemented",L31<>"Yes"),"Validate evidence",IF(AND(D31="Yes",E31="N/A"),"Status conflict",IF(AND(D31="No",E31<>"N/A"),"Status conflict","OK"))) -> OK
A32: 5. Organizational | B32: 5.31 | C32: Legal, statutory, regulatory and contractual requirements | D32: Yes | E32: Implemented | F32: 200+ enterprise contracts, GDPR processing in eu-west-1 and customer security addenda tracked in a register (R-011). | G32: EV-17 | H32: R-011 | L32: Pending | M32: =IF(AND(E32="Implemented",L32<>"Yes"),"Validate evidence",IF(AND(D32="Yes",E32="N/A"),"Status conflict",IF(AND(D32="No",E32<>"N/A"),"Status conflict","OK"))) -> Validate evidence
A33: 5. Organizational | B33: 5.32 | C33: Intellectual property rights | D33: Yes | E33: Partial | F33: Software and open-source licence compliance for platform code (R-009). Licence register and scanning to be completed. | G33: EV-42 | H33: R-009 | L33: n/a | M33: =IF(AND(E33="Implemented",L33<>"Yes"),"Validate evidence",IF(AND(D33="Yes",E33="N/A"),"Status conflict",IF(AND(D33="No",E33<>"N/A"),"Status conflict","OK"))) -> OK
A34: 5. Organizational | B34: 5.33 | C34: Protection of records | D34: Yes | E34: Partial | F34: Protects audit trails, contracts and security records (R-011, R-012). Retention schedule approved; immutable log storage being rolled out. | G34: EV-41 | H34: R-011, R-012 | L34: n/a | M34: =IF(AND(E34="Implemented",L34<>"Yes"),"Validate evidence",IF(AND(D34="Yes",E34="N/A"),"Status conflict",IF(AND(D34="No",E34<>"N/A"),"Status conflict","OK"))) -> OK
A35: 5. Organizational | B35: 5.34 | C35: Privacy and protection of PII | D35: Yes | E35: Partial | F35: Progress acts as processor of customer personal data (R-011, R-012). RoPA, DPAs and DSAR procedure operate; DPIA coverage incomplete. | G35: EV-18 | H35: R-011, R-012 | L35: n/a | M35: =IF(AND(E35="Implemented",L35<>"Yes"),"Validate evidence",IF(AND(D35="Yes",E35="N/A"),"Status conflict",IF(AND(D35="No",E35<>"N/A"),"Status conflict","OK"))) -> OK
A36: 5. Organizational | B36: 5.35 | C36: Independent review of information security | D36: Yes | E36: Planned | F36: Independent assurance on ISMS design and operation (clause 9.2). First internal audit scheduled before Stage 1. | G36: EV-19 | J36: A-20 | L36: n/a | M36: =IF(AND(E36="Implemented",L36<>"Yes"),"Validate evidence",IF(AND(D36="Yes",E36="N/A"),"Status conflict",IF(AND(D36="No",E36<>"N/A"),"Status conflict","OK"))) -> OK
A37: 5. Organizational | B37: 5.36 | C37: Compliance with policies, rules and standards for information security | D37: Yes | E37: Partial | F37: Checked through AWS Config and MDM compliance reports (R-003, R-004); manager attestation cycle not yet running. | G37: EV-19, EV-23, EV-31 | H37: R-003, R-004 | L37: n/a | M37: =IF(AND(E37="Implemented",L37<>"Yes"),"Validate evidence",IF(AND(D37="Yes",E37="N/A"),"Status conflict",IF(AND(D37="No",E37<>"N/A"),"Status conflict","OK"))) -> OK
A38: 5. Organizational | B38: 5.37 | C38: Documented operating procedures | D38: Yes | E38: Partial | F38: Runbooks for deployment, access, incident and backup held in the wiki (R-003, R-006); ownership and review dates incomplete. | G38: EV-39 | H38: R-003, R-006 | L38: n/a | M38: =IF(AND(E38="Implemented",L38<>"Yes"),"Validate evidence",IF(AND(D38="Yes",E38="N/A"),"Status conflict",IF(AND(D38="No",E38<>"N/A"),"Status conflict","OK"))) -> OK
A39: 6. People | B39: 6.1 | C39: Screening | D39: Yes | E39: Implemented | F39: Background checks proportionate to access to customer data (R-004), within local employment law. | G39: EV-20 | H39: R-004 | L39: Pending | M39: =IF(AND(E39="Implemented",L39<>"Yes"),"Validate evidence",IF(AND(D39="Yes",E39="N/A"),"Status conflict",IF(AND(D39="No",E39<>"N/A"),"Status conflict","OK"))) -> Validate evidence
A40: 6. People | B40: 6.2 | C40: Terms and conditions of employment | D40: Yes | E40: Implemented | F40: Contracts bind staff to security duties, including remote-working obligations (R-004). | G40: EV-20 | H40: R-004 | L40: Pending | M40: =IF(AND(E40="Implemented",L40<>"Yes"),"Validate evidence",IF(AND(D40="Yes",E40="N/A"),"Status conflict",IF(AND(D40="No",E40<>"N/A"),"Status conflict","OK"))) -> Validate evidence
A41: 6. People | B41: 6.3 | C41: Information security awareness, education and training | D41: Yes | E41: Partial | F41: Annual awareness and phishing simulation run (R-004, R-007); role-based secure-coding and cloud-admin training planned. | G41: EV-21 | H41: R-004, R-007 | J41: A-19 | L41: n/a | M41: =IF(AND(E41="Implemented",L41<>"Yes"),"Validate evidence",IF(AND(D41="Yes",E41="N/A"),"Status conflict",IF(AND(D41="No",E41<>"N/A"),"Status conflict","OK"))) -> OK
A42: 6. People | B42: 6.4 | C42: Disciplinary process | D42: Yes | E42: Implemented | F42: Formal sanction process deters policy breaches (R-004). | G42: EV-20 | H42: R-004 | L42: Pending | M42: =IF(AND(E42="Implemented",L42<>"Yes"),"Validate evidence",IF(AND(D42="Yes",E42="N/A"),"Status conflict",IF(AND(D42="No",E42<>"N/A"),"Status conflict","OK"))) -> Validate evidence
A43: 6. People | B43: 6.5 | C43: Responsibilities after termination or change of employment | D43: Yes | E43: Implemented | F43: Leaver and mover checklist covers access removal, asset return and continuing confidentiality (R-002, R-004). | G43: EV-20, EV-24 | H43: R-002, R-004 | L43: Pending | M43: =IF(AND(E43="Implemented",L43<>"Yes"),"Validate evidence",IF(AND(D43="Yes",E43="N/A"),"Status conflict",IF(AND(D43="No",E43<>"N/A"),"Status conflict","OK"))) -> Validate evidence
A44: 6. People | B44: 6.6 | C44: Confidentiality or non-disclosure agreements | D44: Yes | E44: Implemented | F44: NDAs for staff, contractors, customers and suppliers (R-004, R-011). | G44: EV-20, EV-13 | H44: R-004, R-011 | L44: Pending | M44: =IF(AND(E44="Implemented",L44<>"Yes"),"Validate evidence",IF(AND(D44="Yes",E44="N/A"),"Status conflict",IF(AND(D44="No",E44<>"N/A"),"Status conflict","OK"))) -> Validate evidence
A45: 6. People | B45: 6.7 | C45: Remote working | D45: Yes | E45: Partial | F45: The entire workforce is remote, so this is central to scope (R-001, R-002, R-007). Remote working standard issued; home-network guidance and spot-check programme still maturing. | G45: EV-22, EV-23 | H45: R-001, R-002, R-007 | L45: n/a | M45: =IF(AND(E45="Implemented",L45<>"Yes"),"Validate evidence",IF(AND(D45="Yes",E45="N/A"),"Status conflict",IF(AND(D45="No",E45<>"N/A"),"Status conflict","OK"))) -> OK
A46: 6. People | B46: 6.8 | C46: Information security event reporting | D46: Yes | E46: Implemented | F46: One channel (security mailbox and chat channel) for loss, phishing and suspicious activity, with reporting statistics (R-002, R-007). | G46: EV-50 | H46: R-002, R-007 | L46: Pending | M46: =IF(AND(E46="Implemented",L46<>"Yes"),"Validate evidence",IF(AND(D46="Yes",E46="N/A"),"Status conflict",IF(AND(D46="No",E46<>"N/A"),"Status conflict","OK"))) -> Validate evidence
A47: 7. Physical | B47: 7.1 | C47: Physical security perimeters | D47: No | E47: N/A | F47: EXCLUDED. Progress controls no premises or secure perimeter; all staff work remotely and production runs in AWS. Residual laptop risk (R-002) treated by 8.1 and 7.9. | G47: EV-43 | I47: ED-01 | L47: n/a | M47: =IF(AND(E47="Implemented",L47<>"Yes"),"Validate evidence",IF(AND(D47="Yes",E47="N/A"),"Status conflict",IF(AND(D47="No",E47<>"N/A"),"Status conflict","OK"))) -> OK
A48: 7. Physical | B48: 7.2 | C48: Physical entry | D48: No | E48: N/A | F48: EXCLUDED. No facilities with entry points. Access to information is controlled logically through 5.15, 5.18 and 8.5. | G48: EV-43 | I48: ED-01 | L48: n/a | M48: =IF(AND(E48="Implemented",L48<>"Yes"),"Validate evidence",IF(AND(D48="Yes",E48="N/A"),"Status conflict",IF(AND(D48="No",E48<>"N/A"),"Status conflict","OK"))) -> OK
A49: 7. Physical | B49: 7.3 | C49: Securing offices, rooms and facilities | D49: No | E49: N/A | F49: EXCLUDED. No offices, rooms or facilities. Employee homes are not company facilities; their risk is treated by 6.7, 7.7 and 7.9. | G49: EV-43 | I49: ED-01 | L49: n/a | M49: =IF(AND(E49="Implemented",L49<>"Yes"),"Validate evidence",IF(AND(D49="Yes",E49="N/A"),"Status conflict",IF(AND(D49="No",E49<>"N/A"),"Status conflict","OK"))) -> OK
A50: 7. Physical | B50: 7.4 | C50: Physical security monitoring | D50: No | E50: N/A | F50: EXCLUDED. No premises to monitor. AWS monitors its data centres; assurance obtained under 5.22; logical monitoring by 8.15 and 8.16. | G50: EV-12, EV-43 | I50: ED-02 | L50: n/a | M50: =IF(AND(E50="Implemented",L50<>"Yes"),"Validate evidence",IF(AND(D50="Yes",E50="N/A"),"Status conflict",IF(AND(D50="No",E50<>"N/A"),"Status conflict","OK"))) -> OK
A51: 7. Physical | B51: 7.5 | C51: Protecting against physical and environmental threats | D51: No | E51: N/A | F51: EXCLUDED. No company site exposed to fire, flood or power loss. AWS Availability Zone design inherited (R-005); service impact treated by 5.29, 5.30 and 8.14 (R-006). | G51: EV-12, EV-43 | I51: ED-02 | L51: n/a | M51: =IF(AND(E51="Implemented",L51<>"Yes"),"Validate evidence",IF(AND(D51="Yes",E51="N/A"),"Status conflict",IF(AND(D51="No",E51<>"N/A"),"Status conflict","OK"))) -> OK
A52: 7. Physical | B52: 7.6 | C52: Working in secure areas | D52: No | E52: N/A | F52: EXCLUDED. No secure areas exist. Sensitive work is protected logically through 8.2 and 8.3. | G52: EV-43 | I52: ED-01 | L52: n/a | M52: =IF(AND(E52="Implemented",L52<>"Yes"),"Validate evidence",IF(AND(D52="Yes",E52="N/A"),"Status conflict",IF(AND(D52="No",E52<>"N/A"),"Status conflict","OK"))) -> OK
A53: 7. Physical | B53: 7.7 | C53: Clear desk and clear screen | D53: Yes | E53: Partial | F53: Applies to remote workers in homes, cafes and travel (R-001, R-002, R-007). MDM enforces auto-lock; clear-desk guidance in the remote working standard; no-printing rule. | G53: EV-22, EV-23 | H53: R-001, R-002, R-007 | L53: n/a | M53: =IF(AND(E53="Implemented",L53<>"Yes"),"Validate evidence",IF(AND(D53="Yes",E53="N/A"),"Status conflict",IF(AND(D53="No",E53<>"N/A"),"Status conflict","OK"))) -> OK
A54: 7. Physical | B54: 7.8 | C54: Equipment siting and protection | D54: No | E54: N/A | F54: EXCLUDED. No company equipment is sited in company premises; servers are AWS-operated. Endpoint protection covered by 7.9 and 8.1. | G54: EV-24, EV-43 | I54: ED-03 | L54: n/a | M54: =IF(AND(E54="Implemented",L54<>"Yes"),"Validate evidence",IF(AND(D54="Yes",E54="N/A"),"Status conflict",IF(AND(D54="No",E54<>"N/A"),"Status conflict","OK"))) -> OK
A55: 7. Physical | B55: 7.9 | C55: Security of assets off-premises | D55: Yes | E55: Implemented | F55: Primary physical control for the business: laptops are the only company-owned assets outside AWS and are always off-premises (R-002). Full-disk encryption, remote wipe and travel guidance enforced. | G55: EV-23, EV-24 | H55: R-002 | L55: Pending | M55: =IF(AND(E55="Implemented",L55<>"Yes"),"Validate evidence",IF(AND(D55="Yes",E55="N/A"),"Status conflict",IF(AND(D55="No",E55<>"N/A"),"Status conflict","OK"))) -> Validate evidence
A56: 7. Physical | B56: 7.10 | C56: Storage media | D56: Yes | E56: Partial | F56: Laptops and removable media can carry customer-adjacent data (R-002, R-004). USB mass storage restricted by MDM policy; formal media handling rules being finalised. | G56: EV-22, EV-23 | H56: R-002, R-004 | L56: n/a | M56: =IF(AND(E56="Implemented",L56<>"Yes"),"Validate evidence",IF(AND(D56="Yes",E56="N/A"),"Status conflict",IF(AND(D56="No",E56<>"N/A"),"Status conflict","OK"))) -> OK
A57: 7. Physical | B57: 7.11 | C57: Supporting utilities | D57: No | E57: N/A | F57: EXCLUDED. No company site with power, cooling or telecoms. AWS provides resilient utilities for the hosting layer (R-005, R-006). | G57: EV-12, EV-43 | I57: ED-02 | L57: n/a | M57: =IF(AND(E57="Implemented",L57<>"Yes"),"Validate evidence",IF(AND(D57="Yes",E57="N/A"),"Status conflict",IF(AND(D57="No",E57<>"N/A"),"Status conflict","OK"))) -> OK
A58: 7. Physical | B58: 7.12 | C58: Cabling security | D58: No | E58: N/A | F58: EXCLUDED. Progress owns no cabling; networks are home ISPs and AWS. Data in transit protected by 8.24. | G58: EV-43 | I58: ED-03 | L58: n/a | M58: =IF(AND(E58="Implemented",L58<>"Yes"),"Validate evidence",IF(AND(D58="Yes",E58="N/A"),"Status conflict",IF(AND(D58="No",E58<>"N/A"),"Status conflict","OK"))) -> OK
A59: 7. Physical | B59: 7.13 | C59: Equipment maintenance | D59: Yes | E59: Partial | F59: Laptop repair, firmware and warranty servicing must not expose data (R-002). Approved repair route with encrypted disks; firmware patching via MDM. | G59: EV-23, EV-24 | H59: R-002 | L59: n/a | M59: =IF(AND(E59="Implemented",L59<>"Yes"),"Validate evidence",IF(AND(D59="Yes",E59="N/A"),"Status conflict",IF(AND(D59="No",E59<>"N/A"),"Status conflict","OK"))) -> OK
A60: 7. Physical | B60: 7.14 | C60: Secure disposal or re-use of equipment | D60: Yes | E60: Partial | F60: End-of-life laptops must be wiped and certified (R-002, R-011, R-012). Cloud media sanitisation inherited from AWS; disposal certificates being collected. | G60: EV-24, EV-33 | H60: R-002, R-011, R-012 | L60: n/a | M60: =IF(AND(E60="Implemented",L60<>"Yes"),"Validate evidence",IF(AND(D60="Yes",E60="N/A"),"Status conflict",IF(AND(D60="No",E60<>"N/A"),"Status conflict","OK"))) -> OK
A61: 8. Technological | B61: 8.1 | C61: User endpoint devices | D61: Yes | E61: Implemented | F61: Laptops are the main access point to customer-adjacent systems (R-001, R-002, R-007). MDM enforces encryption, patching, EDR and screen lock. | G61: EV-23 | H61: R-001, R-002, R-007 | L61: Pending | M61: =IF(AND(E61="Implemented",L61<>"Yes"),"Validate evidence",IF(AND(D61="Yes",E61="N/A"),"Status conflict",IF(AND(D61="No",E61<>"N/A"),"Status conflict","OK"))) -> Validate evidence
A62: 8. Technological | B62: 8.2 | C62: Privileged access rights | D62: Yes | E62: Partial | F62: Admin rights to AWS accounts concentrated in few roles (R-001, R-003, R-004). Just-in-time elevation and periodic review being completed. | G62: EV-11 | H62: R-001, R-003, R-004 | J62: A-16 | L62: n/a | M62: =IF(AND(E62="Implemented",L62<>"Yes"),"Validate evidence",IF(AND(D62="Yes",E62="N/A"),"Status conflict",IF(AND(D62="No",E62<>"N/A"),"Status conflict","OK"))) -> OK
A63: 8. Technological | B63: 8.3 | C63: Information access restriction | D63: Yes | E63: Implemented | F63: Restricts customer data to authorised roles and service identities through IAM, resource policies and per-account separation (R-001, R-004). | G63: EV-11, EV-37 | H63: R-001, R-004 | L63: Pending | M63: =IF(AND(E63="Implemented",L63<>"Yes"),"Validate evidence",IF(AND(D63="Yes",E63="N/A"),"Status conflict",IF(AND(D63="No",E63<>"N/A"),"Status conflict","OK"))) -> Validate evidence
A64: 8. Technological | B64: 8.4 | C64: Access to source code | D64: Yes | E64: Implemented | F64: Source code and infrastructure-as-code are core IP and the path to production (R-004, R-009, R-010). Organisation SSO, branch protection and least-privilege repositories. | G64: EV-26 | H64: R-004, R-009, R-010 | L64: Pending | M64: =IF(AND(E64="Implemented",L64<>"Yes"),"Validate evidence",IF(AND(D64="Yes",E64="N/A"),"Status conflict",IF(AND(D64="No",E64<>"N/A"),"Status conflict","OK"))) -> Validate evidence
A65: 8. Technological | B65: 8.5 | C65: Secure authentication | D65: Yes | E65: Implemented | F65: SSO with MFA for all users and stronger methods for administrators; conditional access (R-001, R-007, R-013). | G65: EV-46 | H65: R-001, R-007, R-013 | L65: Pending | M65: =IF(AND(E65="Implemented",L65<>"Yes"),"Validate evidence",IF(AND(D65="Yes",E65="N/A"),"Status conflict",IF(AND(D65="No",E65<>"N/A"),"Status conflict","OK"))) -> Validate evidence
A66: 8. Technological | B66: 8.6 | C66: Capacity management | D66: Yes | E66: Partial | F66: Platform availability under customer load (R-006, R-013). Auto-scaling and dashboards exist; capacity forecasting not formal. | G66: EV-36 | H66: R-006, R-013 | L66: n/a | M66: =IF(AND(E66="Implemented",L66<>"Yes"),"Validate evidence",IF(AND(D66="Yes",E66="N/A"),"Status conflict",IF(AND(D66="No",E66<>"N/A"),"Status conflict","OK"))) -> OK
A67: 8. Technological | B67: 8.7 | C67: Protection against malware | D67: Yes | E67: Implemented | F67: EDR and anti-malware on all laptops; workload protection in AWS (R-007, R-008). | G67: EV-23 | H67: R-007, R-008 | L67: Pending | M67: =IF(AND(E67="Implemented",L67<>"Yes"),"Validate evidence",IF(AND(D67="Yes",E67="N/A"),"Status conflict",IF(AND(D67="No",E67<>"N/A"),"Status conflict","OK"))) -> Validate evidence
A68: 8. Technological | B68: 8.8 | C68: Management of technical vulnerabilities | D68: Yes | E68: Partial | F68: Scanning of hosts, containers and dependencies (R-003, R-008, R-009). Remediation SLAs and reporting not yet consistently evidenced. | G68: EV-25 | H68: R-003, R-008, R-009 | J68: A-12 | L68: n/a | M68: =IF(AND(E68="Implemented",L68<>"Yes"),"Validate evidence",IF(AND(D68="Yes",E68="N/A"),"Status conflict",IF(AND(D68="No",E68<>"N/A"),"Status conflict","OK"))) -> OK
A69: 8. Technological | B69: 8.9 | C69: Configuration management | D69: Yes | E69: Partial | F69: Treats R-003 (Critical) and R-010: baselines via infrastructure-as-code and AWS Config rules. Drift remediation, exception process and secrets-in-config checks still maturing. | G69: EV-31 | H69: R-003, R-010 | J69: A-10 | L69: n/a | M69: =IF(AND(E69="Implemented",L69<>"Yes"),"Validate evidence",IF(AND(D69="Yes",E69="N/A"),"Status conflict",IF(AND(D69="No",E69<>"N/A"),"Status conflict","OK"))) -> OK
A70: 8. Technological | B70: 8.10 | C70: Information deletion | D70: Yes | E70: Partial | F70: Deletion of customer data at contract end and of data on retired laptops (R-011, R-012). Offboarding runbook exists; deletion verification evidence limited. | G70: EV-33 | H70: R-011, R-012 | L70: n/a | M70: =IF(AND(E70="Implemented",L70<>"Yes"),"Validate evidence",IF(AND(D70="Yes",E70="N/A"),"Status conflict",IF(AND(D70="No",E70<>"N/A"),"Status conflict","OK"))) -> OK
A71: 8. Technological | B71: 8.11 | C71: Data masking | D71: Yes | E71: Planned | F71: Analytics datasets need masking in non-production and support access (R-001, R-011). Design approved; implementation scheduled in Wave 1. | G71: EV-38 | H71: R-001, R-011 | J71: A-13 | L71: n/a | M71: =IF(AND(E71="Implemented",L71<>"Yes"),"Validate evidence",IF(AND(D71="Yes",E71="N/A"),"Status conflict",IF(AND(D71="No",E71<>"N/A"),"Status conflict","OK"))) -> OK
A72: 8. Technological | B72: 8.12 | C72: Data leakage prevention | D72: Yes | E72: Planned | F72: Prevents exfiltration through insiders or misconfiguration (R-001, R-003, R-004). S3 public-access blocks exist; endpoint and egress DLP planned. | G72: EV-49 | H72: R-001, R-003, R-004 | J72: A-17 | L72: n/a | M72: =IF(AND(E72="Implemented",L72<>"Yes"),"Validate evidence",IF(AND(D72="Yes",E72="N/A"),"Status conflict",IF(AND(D72="No",E72<>"N/A"),"Status conflict","OK"))) -> OK
A73: 8. Technological | B73: 8.13 | C73: Information backup | D73: Yes | E73: Partial | F73: AWS Backup policies configured with encryption and retention aligned to contracts (R-006, R-008, R-012). Scheduled restore-test evidence missing. | G73: EV-29 | H73: R-006, R-008, R-012 | J73: A-18 | L73: n/a | M73: =IF(AND(E73="Implemented",L73<>"Yes"),"Validate evidence",IF(AND(D73="Yes",E73="N/A"),"Status conflict",IF(AND(D73="No",E73<>"N/A"),"Status conflict","OK"))) -> OK
A74: 8. Technological | B74: 8.14 | C74: Redundancy of information processing facilities | D74: Yes | E74: Implemented | F74: Multi-AZ architecture for production services (R-005, R-006, R-008). | G74: EV-16, EV-32 | H74: R-005, R-006, R-008 | L74: Pending | M74: =IF(AND(E74="Implemented",L74<>"Yes"),"Validate evidence",IF(AND(D74="Yes",E74="N/A"),"Status conflict",IF(AND(D74="No",E74<>"N/A"),"Status conflict","OK"))) -> Validate evidence
A75: 8. Technological | B75: 8.15 | C75: Logging | D75: Yes | E75: Implemented | F75: CloudTrail, VPC flow logs, application and identity-provider logs centralised (R-001, R-003, R-004, R-013). | G75: EV-28 | H75: R-001, R-003, R-004, R-013 | L75: Pending | M75: =IF(AND(E75="Implemented",L75<>"Yes"),"Validate evidence",IF(AND(D75="Yes",E75="N/A"),"Status conflict",IF(AND(D75="No",E75<>"N/A"),"Status conflict","OK"))) -> Validate evidence
A76: 8. Technological | B76: 8.16 | C76: Monitoring activities | D76: Yes | E76: Partial | F76: GuardDuty and Security Hub alerts reviewed (R-001, R-003, R-004, R-007). Alert tuning and out-of-hours response still maturing. | G76: EV-28 | H76: R-001, R-003, R-004, R-007 | J76: A-11 | L76: n/a | M76: =IF(AND(E76="Implemented",L76<>"Yes"),"Validate evidence",IF(AND(D76="Yes",E76="N/A"),"Status conflict",IF(AND(D76="No",E76<>"N/A"),"Status conflict","OK"))) -> OK
A77: 8. Technological | B77: 8.17 | C77: Clock synchronization | D77: Yes | E77: Implemented | F77: Systems use AWS Time Sync, giving reliable log correlation for investigations (R-001). | G77: EV-47 | H77: R-001 | L77: Pending | M77: =IF(AND(E77="Implemented",L77<>"Yes"),"Validate evidence",IF(AND(D77="Yes",E77="N/A"),"Status conflict",IF(AND(D77="No",E77<>"N/A"),"Status conflict","OK"))) -> Validate evidence
A78: 8. Technological | B78: 8.18 | C78: Use of privileged utility programs | D78: Yes | E78: Partial | F78: Admin tools (session manager, CLI, database consoles) can bypass application controls (R-001, R-004). Use is restricted and logged; formal tool inventory pending. | G78: EV-11, EV-28 | H78: R-001, R-004 | L78: n/a | M78: =IF(AND(E78="Implemented",L78<>"Yes"),"Validate evidence",IF(AND(D78="Yes",E78="N/A"),"Status conflict",IF(AND(D78="No",E78<>"N/A"),"Status conflict","OK"))) -> OK
A79: 8. Technological | B79: 8.19 | C79: Installation of software on operational systems | D79: Yes | E79: Implemented | F79: Production software deployed only through CI/CD from reviewed code (R-003, R-009, R-010); endpoint software governed by MDM. | G79: EV-26, EV-31 | H79: R-003, R-009, R-010 | L79: Pending | M79: =IF(AND(E79="Implemented",L79<>"Yes"),"Validate evidence",IF(AND(D79="Yes",E79="N/A"),"Status conflict",IF(AND(D79="No",E79<>"N/A"),"Status conflict","OK"))) -> Validate evidence
A80: 8. Technological | B80: 8.20 | C80: Networks security | D80: Yes | E80: Implemented | F80: VPC design, security groups and WAF protect API endpoints (R-001, R-003, R-013). | G80: EV-32 | H80: R-001, R-003, R-013 | L80: Pending | M80: =IF(AND(E80="Implemented",L80<>"Yes"),"Validate evidence",IF(AND(D80="Yes",E80="N/A"),"Status conflict",IF(AND(D80="No",E80<>"N/A"),"Status conflict","OK"))) -> Validate evidence
A81: 8. Technological | B81: 8.21 | C81: Security of network services | D81: Yes | E81: Partial | F81: Relies on AWS network services and their assurance (R-005, R-013). Service security requirements documented; supplier evidence review ongoing. | G81: EV-32, EV-12 | H81: R-005, R-013 | L81: n/a | M81: =IF(AND(E81="Implemented",L81<>"Yes"),"Validate evidence",IF(AND(D81="Yes",E81="N/A"),"Status conflict",IF(AND(D81="No",E81<>"N/A"),"Status conflict","OK"))) -> OK
A82: 8. Technological | B82: 8.22 | C82: Segregation of networks | D82: Yes | E82: Implemented | F82: Separate AWS accounts and VPC segments for production and non-production (R-001, R-003, R-008). | G82: EV-32, EV-37 | H82: R-001, R-003, R-008 | L82: Pending | M82: =IF(AND(E82="Implemented",L82<>"Yes"),"Validate evidence",IF(AND(D82="Yes",E82="N/A"),"Status conflict",IF(AND(D82="No",E82<>"N/A"),"Status conflict","OK"))) -> Validate evidence
A83: 8. Technological | B83: 8.23 | C83: Web filtering | D83: Yes | E83: Planned | F83: Reduces phishing and malware exposure on remote laptops (R-007). DNS filtering through MDM scheduled in Wave 1. | G83: EV-45 | H83: R-007 | J83: A-06 | L83: n/a | M83: =IF(AND(E83="Implemented",L83<>"Yes"),"Validate evidence",IF(AND(D83="Yes",E83="N/A"),"Status conflict",IF(AND(D83="No",E83<>"N/A"),"Status conflict","OK"))) -> OK
A84: 8. Technological | B84: 8.24 | C84: Use of cryptography | D84: Yes | E84: Implemented | F84: Encryption at rest and in transit using AWS KMS keys (R-001, R-002, R-005). Progress generates no keys but defines key use, rotation and access rules. | G84: EV-30 | H84: R-001, R-002, R-005 | L84: Pending | M84: =IF(AND(E84="Implemented",L84<>"Yes"),"Validate evidence",IF(AND(D84="Yes",E84="N/A"),"Status conflict",IF(AND(D84="No",E84<>"N/A"),"Status conflict","OK"))) -> Validate evidence
A85: 8. Technological | B85: 8.25 | C85: Secure development life cycle | D85: Yes | E85: Implemented | F85: Defines security activities from design to release (R-003, R-009, R-013). | G85: EV-26 | H85: R-003, R-009, R-013 | L85: Pending | M85: =IF(AND(E85="Implemented",L85<>"Yes"),"Validate evidence",IF(AND(D85="Yes",E85="N/A"),"Status conflict",IF(AND(D85="No",E85<>"N/A"),"Status conflict","OK"))) -> Validate evidence
A86: 8. Technological | B86: 8.26 | C86: Application security requirements | D86: Yes | E86: Partial | F86: API-only product: authentication, authorisation, rate limiting and input validation requirements (R-001, R-013). Documented requirement set still being completed. | G86: EV-26 | H86: R-001, R-013 | L86: n/a | M86: =IF(AND(E86="Implemented",L86<>"Yes"),"Validate evidence",IF(AND(D86="Yes",E86="N/A"),"Status conflict",IF(AND(D86="No",E86<>"N/A"),"Status conflict","OK"))) -> OK
A87: 8. Technological | B87: 8.27 | C87: Secure system architecture and engineering principles | D87: Yes | E87: Partial | F87: Secure-by-design patterns for AWS (R-003, R-013). Principles exist; threat modelling not yet routine. | G87: EV-14, EV-32 | H87: R-003, R-013 | L87: n/a | M87: =IF(AND(E87="Implemented",L87<>"Yes"),"Validate evidence",IF(AND(D87="Yes",E87="N/A"),"Status conflict",IF(AND(D87="No",E87<>"N/A"),"Status conflict","OK"))) -> OK
A88: 8. Technological | B88: 8.28 | C88: Secure coding | D88: Yes | E88: Partial | F88: Secure coding standard, peer review, SAST and secret scanning (R-009, R-010, R-013). Developer role-based training links to 6.3. | G88: EV-26 | H88: R-009, R-010, R-013 | L88: n/a | M88: =IF(AND(E88="Implemented",L88<>"Yes"),"Validate evidence",IF(AND(D88="Yes",E88="N/A"),"Status conflict",IF(AND(D88="No",E88<>"N/A"),"Status conflict","OK"))) -> OK
A89: 8. Technological | B89: 8.29 | C89: Security testing in development and acceptance | D89: Yes | E89: Partial | F89: SAST, SCA and DAST in pipeline plus annual third-party penetration test (R-009, R-010, R-013). Acceptance criteria not formalised. | G89: EV-25, EV-26 | H89: R-009, R-010, R-013 | L89: n/a | M89: =IF(AND(E89="Implemented",L89<>"Yes"),"Validate evidence",IF(AND(D89="Yes",E89="N/A"),"Status conflict",IF(AND(D89="No",E89<>"N/A"),"Status conflict","OK"))) -> OK
A90: 8. Technological | B90: 8.30 | C90: Outsourced development | D90: No | E90: N/A | F90: EXCLUDED. All code is written in-house. Contractors or agencies would trigger re-evaluation; 8.25, 8.28 and 5.19-5.21 are the fall-back controls. | G90: EV-43 | I90: ED-04 | L90: n/a | M90: =IF(AND(E90="Implemented",L90<>"Yes"),"Validate evidence",IF(AND(D90="Yes",E90="N/A"),"Status conflict",IF(AND(D90="No",E90<>"N/A"),"Status conflict","OK"))) -> OK
A91: 8. Technological | B91: 8.31 | C91: Separation of development, test and production environments | D91: Yes | E91: Implemented | F91: Separate AWS accounts keep untested change and customer data out of lower environments (R-001, R-003). | G91: EV-37 | H91: R-001, R-003 | L91: Pending | M91: =IF(AND(E91="Implemented",L91<>"Yes"),"Validate evidence",IF(AND(D91="Yes",E91="N/A"),"Status conflict",IF(AND(D91="No",E91<>"N/A"),"Status conflict","OK"))) -> Validate evidence
A92: 8. Technological | B92: 8.32 | C92: Change management | D92: Yes | E92: Implemented | F92: Pull-request approval, CI checks and change records for infrastructure and application (R-003). | G92: EV-27 | H92: R-003 | L92: Pending | M92: =IF(AND(E92="Implemented",L92<>"Yes"),"Validate evidence",IF(AND(D92="Yes",E92="N/A"),"Status conflict",IF(AND(D92="No",E92<>"N/A"),"Status conflict","OK"))) -> Validate evidence
A93: 8. Technological | B93: 8.33 | C93: Test information | D93: Yes | E93: Planned | F93: Test data must not contain real customer data without safeguards (R-001, R-011). Policy approved; synthetic data tooling planned. | G93: EV-38 | H93: R-001, R-011 | J93: A-14 | L93: n/a | M93: =IF(AND(E93="Implemented",L93<>"Yes"),"Validate evidence",IF(AND(D93="Yes",E93="N/A"),"Status conflict",IF(AND(D93="No",E93<>"N/A"),"Status conflict","OK"))) -> OK
A94: 8. Technological | B94: 8.34 | C94: Protection of information systems during audit testing | D94: Yes | E94: Planned | F94: Audits, scans and penetration tests on production must not disrupt service or expose data (R-001, R-006). Audit-testing protocol to be written. | G94: EV-48 | H94: R-006 | J94: A-05 | L94: n/a | M94: =IF(AND(E94="Implemented",L94<>"Yes"),"Validate evidence",IF(AND(D94="Yes",E94="N/A"),"Status conflict",IF(AND(D94="No",E94<>"N/A"),"Status conflict","OK"))) -> OK

Sheet Exclusions
A1: Exclusion Register
A2: Each exclusion passed the five-part test: subject absent, no dependent risk, alternative named, inheritance evidenced, trigger defined.
A4: Ref | B4: Control | C4: Dossier | D4: Reason for exclusion | E4: Alternative or inherited measure | F4: Re-evaluation trigger | G4: Evidence
A5: 7.1 | B5: Physical security perimeters | C5: ED-01 | D5: No company premises; remote-first since founding | E5: 8.1, 7.9; AWS data-centre perimeters via 5.22 | F5: Lease or ownership of any premises | G5: EV-43
A6: 7.2 | B6: Physical entry | C6: ED-01 | D6: No facilities with entry points | E6: 5.15, 5.18, 8.5 (logical access) | F6: Any premises or shared workspace holding company assets | G6: EV-43
A7: 7.3 | B7: Securing offices, rooms and facilities | C7: ED-01 | D7: No offices, rooms or facilities; home offices are not company facilities | E7: 6.7, 7.7, 7.9, 8.1 | F7: Company-controlled office, storage room or lab | G7: EV-43
A8: 7.4 | B8: Physical security monitoring | C8: ED-02 | D8: No premises to monitor; AWS monitors its data centres | E8: 8.15, 8.16; AWS assurance via 5.22 | F8: Loss of AWS assurance evidence or move to non-AWS hosting | G8: EV-12, EV-43
A9: 7.5 | B9: Protecting against physical and environmental threats | C9: ED-02 | D9: No company site; hosting threats inherited from AWS AZ design | E9: 5.29, 5.30, 8.14; AWS assurance via 5.22 | F9: Move to single-AZ or non-AWS hosting; AWS assurance gap | G9: EV-12, EV-43
A10: 7.6 | B10: Working in secure areas | C10: ED-01 | D10: No secure areas exist | E10: 8.2, 8.3 (logical segregation of sensitive work) | F10: Creation of a secure room or lab | G10: EV-43
A11: 7.8 | B11: Equipment siting and protection | C11: ED-03 | D11: No company equipment sited on company premises | E11: 7.9, 8.1; AWS-operated servers | F11: Any on-premises server, network or storage equipment | G11: EV-43
A12: 7.11 | B12: Supporting utilities | C12: ED-02 | D12: No company site with power, cooling or telecoms; AWS provides hosting utilities | E12: 5.30, 8.14; AWS assurance via 5.22 | F12: Any company-operated site or equipment room | G12: EV-12, EV-43
A13: 7.12 | B13: Cabling security | C13: ED-03 | D13: Progress owns no cabling; networks are home ISPs and AWS | E13: 8.24 (encryption in transit), 8.20 | F13: Any company-owned network infrastructure | G13: EV-43
A14: 8.30 | B14: Outsourced development | C14: ED-04 | D14: All development is performed by employees | E14: 8.25, 8.28, 5.19-5.21 as fall-back | F14: Use of any external developer, agency or offshore team | G14: EV-43
A16: Count of exclusions (live): | D16: =COUNTA(A5:A14) -> 10

Sheet Risk Register
A1: Risk Register
A2: R-001 to R-006 from the original brief; R-007 to R-013 are author-proposed and pending ratification by the risk owner. Owners are proposed roles.
A4: Risk ID | B4: Risk description | C4: Likelihood | D4: Impact | E4: Inherent level | F4: Target residual | G4: Treatment | H4: Proposed owner | I4: Source | J4: Applicable controls treating risk (live)
A5: R-001 | B5: Unauthorized access to customer data | C5: Medium | D5: High | E5: High | F5: Medium | G5: Treat | H5: Head of Engineering | I5: Original brief | J5: =COUNTIF(Traceability!E$5:E$97,"●") -> 26
A6: R-002 | B6: Employee laptop theft or loss | C6: Medium | D6: Medium | E6: Medium | F6: Low | G6: Treat | H6: IT Operations Lead | I6: Original brief | J6: =COUNTIF(Traceability!F$5:F$97,"●") -> 13
A7: R-003 | B7: Cloud misconfiguration | C7: High | D7: High | E7: Critical | F7: Medium | G7: Treat (priority) | H7: Cloud Platform Lead | I7: Original brief | J7: =COUNTIF(Traceability!G$5:G$97,"●") -> 23
A8: R-004 | B8: Insider threat | C8: Low | D8: High | E8: Medium | F8: Low | G8: Treat | H8: Head of People | I8: Original brief | J8: =COUNTIF(Traceability!H$5:H$97,"●") -> 24
A9: R-005 | B9: Third-party breach (AWS) | C9: Low | D9: Critical | E9: High | F9: Medium | G9: Treat and share | H9: Head of Engineering | I9: Original brief | J9: =COUNTIF(Traceability!I$5:I$97,"●") -> 10
A10: R-006 | B10: Business continuity failure | C10: Low | D10: High | E10: Medium | F10: Low | G10: Treat | H10: Head of Operations | I10: Original brief | J10: =COUNTIF(Traceability!J$5:J$97,"●") -> 10
A11: R-007 | B11: Phishing or credential theft against remote staff | C11: High | D11: Medium | E11: High | F11: Medium | G11: Treat | H11: IT Operations Lead | I11: Author-proposed | J11: =COUNTIF(Traceability!K$5:K$97,"●") -> 14
A12: R-008 | B12: Ransomware or destructive attack on cloud workloads and backups | C12: Low | D12: Critical | E12: High | F12: Medium | G12: Treat | H12: Cloud Platform Lead | I12: Author-proposed | J12: =COUNTIF(Traceability!L$5:L$97,"●") -> 8
A13: R-009 | B13: Software supply-chain compromise | C13: Medium | D13: High | E13: High | F13: Medium | G13: Treat | H13: Head of Engineering | I13: Author-proposed | J13: =COUNTIF(Traceability!M$5:M$97,"●") -> 10
A14: R-010 | B14: Secrets or credentials exposed in code or pipelines | C14: Medium | D14: High | E14: High | F14: Low | G14: Treat | H14: Head of Engineering | I14: Author-proposed | J14: =COUNTIF(Traceability!N$5:N$97,"●") -> 6
A15: R-011 | B15: Non-compliance with GDPR processor duties or customer contract terms | C15: Medium | D15: High | E15: High | F15: Medium | G15: Treat and share | H15: Data Protection Lead | I15: Author-proposed | J15: =COUNTIF(Traceability!O$5:O$97,"●") -> 13
A16: R-012 | B16: Customer data retained beyond contract or not deleted | C16: Medium | D16: Medium | E16: Medium | F16: Low | G16: Treat | H16: Data Protection Lead | I16: Author-proposed | J16: =COUNTIF(Traceability!P$5:P$97,"●") -> 6
A17: R-013 | B17: API abuse: broken authorization, injection or denial of service | C17: Medium | D17: High | E17: High | F17: Medium | G17: Treat | H17: Head of Engineering | I17: Author-proposed | J17: =COUNTIF(Traceability!Q$5:Q$97,"●") -> 11
A19: Methodology note: the source states qualitative ratings without a scoring matrix. Publish the likelihood and impact criteria and matrix (action A-02) before Stage 1.

Sheet Traceability
A1: Risk-to-Control Traceability Matrix
A2: ● = control treats the risk (Annex A controls only; C-01 to C-03 are on the Additional Controls sheet). Counts are live.
A3: Controls per risk (live) | E3: =COUNTIF(E5:E97,"●") -> 26 | F3: =COUNTIF(F5:F97,"●") -> 13 | G3: =COUNTIF(G5:G97,"●") -> 23 | H3: =COUNTIF(H5:H97,"●") -> 24 | I3: =COUNTIF(I5:I97,"●") -> 10 | J3: =COUNTIF(J5:J97,"●") -> 10 | K3: =COUNTIF(K5:K97,"●") -> 14 | L3: =COUNTIF(L5:L97,"●") -> 8 | ... Q3: =COUNTIF(Q5:Q97,"●") -> 11
A4: Ref | B4: Control | C4: Applicable | D4: Status | E4: R-001 | F4: R-002 | G4: R-003 | H4: R-004 | I4: R-005 | J4: R-006 | K4: R-007 | L4: R-008 | M4: R-009 | N4: R-010 | O4: R-011 | P4: R-012 | Q4: R-013 | R4: Risks treated
A5: 5.1 | B5: Policies for information security | C5: =SoA!D2 -> Yes | D5: =SoA!E2 -> Implemented | E5: ● | G5: ● | R5: =COUNTIF(E5:Q5,"●") -> 2
A6: 5.2 | B6: Information security roles and responsibilities | C6: =SoA!D3 -> Yes | D6: =SoA!E3 -> Implemented | G6: ● | H6: ● | R6: =COUNTIF(E6:Q6,"●") -> 2
A7: 5.3 | B7: Segregation of duties | C7: =SoA!D4 -> Yes | D7: =SoA!E4 -> Partial | E7: ● | G7: ● | H7: ● | R7: =COUNTIF(E7:Q7,"●") -> 3
A8: 5.4 | B8: Management responsibilities | C8: =SoA!D5 -> Yes | D8: =SoA!E5 -> Implemented | H8: ● | K8: ● | R8: =COUNTIF(E8:Q8,"●") -> 2
A9: 5.5 | B9: Contact with authorities | C9: =SoA!D6 -> Yes | D9: =SoA!E6 -> Partial | O9: ● | R9: =COUNTIF(E9:Q9,"●") -> 1
A10: 5.6 | B10: Contact with special interest groups | C10: =SoA!D7 -> Yes | D10: =SoA!E7 -> Partial | K10: ● | R10: =COUNTIF(E10:Q10,"●") -> 1
A11: 5.7 | B11: Threat intelligence | C11: =SoA!D8 -> Yes | D11: =SoA!E8 -> Partial | G11: ● | K11: ● | M11: ● | R11: =COUNTIF(E11:Q11,"●") -> 3
A12: 5.8 | B12: Information security in project management | C12: =SoA!D9 -> Yes | D12: =SoA!E9 -> Partial | G12: ● | Q12: ● | R12: =COUNTIF(E12:Q12,"●") -> 2
A13: 5.9 | B13: Inventory of information and other associated assets | C13: =SoA!D10 -> Yes | D13: =SoA!E10 -> Partial | F13: ● | R13: =COUNTIF(E13:Q13,"●") -> 1
A14: 5.10 | B14: Acceptable use of information and other associated assets | C14: =SoA!D11 -> Yes | D14: =SoA!E11 -> Implemented | F14: ● | H14: ● | K14: ● | R14: =COUNTIF(E14:Q14,"●") -> 3
A15: 5.11 | B15: Return of assets | C15: =SoA!D12 -> Yes | D15: =SoA!E12 -> Implemented | F15: ● | H15: ● | R15: =COUNTIF(E15:Q15,"●") -> 2
A16: 5.12 | B16: Classification of information | C16: =SoA!D13 -> Yes | D16: =SoA!E13 -> Partial | E16: ● | O16: ● | P16: ● | R16: =COUNTIF(E16:Q16,"●") -> 3
A17: 5.13 | B17: Labelling of information | C17: =SoA!D14 -> Yes | D17: =SoA!E14 -> Planned | O17: ● | R17: =COUNTIF(E17:Q17,"●") -> 1
A18: 5.14 | B18: Information transfer | C18: =SoA!D15 -> Yes | D18: =SoA!E15 -> Partial | E18: ● | O18: ● | R18: =COUNTIF(E18:Q18,"●") -> 2
A19: 5.15 | B19: Access control | C19: =SoA!D16 -> Yes | D19: =SoA!E16 -> Implemented | E19: ● | H19: ● | R19: =COUNTIF(E19:Q19,"●") -> 2
A20: 5.16 | B20: Identity management | C20: =SoA!D17 -> Yes | D20: =SoA!E17 -> Implemented | E20: ● | H20: ● | R20: =COUNTIF(E20:Q20,"●") -> 2
A21: 5.17 | B21: Authentication information | C21: =SoA!D18 -> Yes | D21: =SoA!E18 -> Implemented | E21: ● | K21: ● | N21: ● | R21: =COUNTIF(E21:Q21,"●") -> 3
A22: 5.18 | B22: Access rights | C22: =SoA!D19 -> Yes | D22: =SoA!E19 -> Partial | E22: ● | H22: ● | R22: =COUNTIF(E22:Q22,"●") -> 2
A23: 5.19 | B23: Information security in supplier relationships | C23: =SoA!D20 -> Yes | D23: =SoA!E20 -> Partial | I23: ● | M23: ● | R23: =COUNTIF(E23:Q23,"●") -> 2
A24: 5.20 | B24: Addressing information security within supplier agreements | C24: =SoA!D21 -> Yes | D24: =SoA!E21 -> Partial | I24: ● | O24: ● | R24: =COUNTIF(E24:Q24,"●") -> 2
A25: 5.21 | B25: Managing information security in the ICT supply chain | C25: =SoA!D22 -> Yes | D25: =SoA!E22 -> Partial | I25: ● | M25: ● | R25: =COUNTIF(E25:Q25,"●") -> 2
A26: 5.22 | B26: Monitoring, review and change management of supplier services | C26: =SoA!D23 -> Yes | D26: =SoA!E23 -> Partial | I26: ● | R26: =COUNTIF(E26:Q26,"●") -> 1
A27: 5.23 | B27: Information security for use of cloud services | C27: =SoA!D24 -> Yes | D27: =SoA!E24 -> Implemented | G27: ● | I27: ● | R27: =COUNTIF(E27:Q27,"●") -> 2
A28: 5.24 | B28: Information security incident management planning and preparation | C28: =SoA!D25 -> Yes | D28: =SoA!E25 -> Implemented | J28: ● | R28: =COUNTIF(E28:Q28,"●") -> 1
A29: 5.25 | B29: Assessment and decision on information security events | C29: =SoA!D26 -> Yes | D29: =SoA!E26 -> Partial | G29: ● | R29: =COUNTIF(E29:Q29,"●") -> 1
A30: 5.26 | B30: Response to information security incidents | C30: =SoA!D27 -> Yes | D30: =SoA!E27 -> Partial | G30: ● | J30: ● | L30: ● | R30: =COUNTIF(E30:Q30,"●") -> 3
A31: 5.27 | B31: Learning from information security incidents | C31: =SoA!D28 -> Yes | D31: =SoA!E28 -> Partial | J31: ● | R31: =COUNTIF(E31:Q31,"●") -> 1
A32: 5.28 | B32: Collection of evidence | C32: =SoA!D29 -> Yes | D32: =SoA!E29 -> Planned | H32: ● | R32: =COUNTIF(E32:Q32,"●") -> 1
A33: 5.29 | B33: Information security during disruption | C33: =SoA!D30 -> Yes | D33: =SoA!E30 -> Partial | I33: ● | J33: ● | L33: ● | R33: =COUNTIF(E33:Q33,"●") -> 3
A34: 5.30 | B34: ICT readiness for business continuity | C34: =SoA!D31 -> Yes | D34: =SoA!E31 -> Partial | I34: ● | J34: ● | L34: ● | R34: =COUNTIF(E34:Q34,"●") -> 3
A35: 5.31 | B35: Legal, statutory, regulatory and contractual requirements | C35: =SoA!D32 -> Yes | D35: =SoA!E32 -> Implemented | O35: ● | R35: =COUNTIF(E35:Q35,"●") -> 1
A36: 5.32 | B36: Intellectual property rights | C36: =SoA!D33 -> Yes | D36: =SoA!E33 -> Partial | M36: ● | R36: =COUNTIF(E36:Q36,"●") -> 1
A37: 5.33 | B37: Protection of records | C37: =SoA!D34 -> Yes | D37: =SoA!E34 -> Partial | O37: ● | P37: ● | R37: =COUNTIF(E37:Q37,"●") -> 2
A38: 5.34 | B38: Privacy and protection of PII | C38: =SoA!D35 -> Yes | D38: =SoA!E35 -> Partial | O38: ● | P38: ● | R38: =COUNTIF(E38:Q38,"●") -> 2
A39: 5.35 | B39: Independent review of information security | C39: =SoA!D36 -> Yes | D39: =SoA!E36 -> Planned | R39: =COUNTIF(E39:Q39,"●") -> 0
A40: 5.36 | B40: Compliance with policies, rules and standards for information security | C40: =SoA!D37 -> Yes | D40: =SoA!E37 -> Partial | G40: ● | H40: ● | R40: =COUNTIF(E40:Q40,"●") -> 2
A41: 5.37 | B41: Documented operating procedures | C41: =SoA!D38 -> Yes | D41: =SoA!E38 -> Partial | G41: ● | J41: ● | R41: =COUNTIF(E41:Q41,"●") -> 2
A42: 6.1 | B42: Screening | C42: =SoA!D39 -> Yes | D42: =SoA!E39 -> Implemented | H42: ● | R42: =COUNTIF(E42:Q42,"●") -> 1
A43: 6.2 | B43: Terms and conditions of employment | C43: =SoA!D40 -> Yes | D43: =SoA!E40 -> Implemented | H43: ● | R43: =COUNTIF(E43:Q43,"●") -> 1
A44: 6.3 | B44: Information security awareness, education and training | C44: =SoA!D41 -> Yes | D44: =SoA!E41 -> Partial | H44: ● | K44: ● | R44: =COUNTIF(E44:Q44,"●") -> 2
A45: 6.4 | B45: Disciplinary process | C45: =SoA!D42 -> Yes | D45: =SoA!E42 -> Implemented | H45: ● | R45: =COUNTIF(E45:Q45,"●") -> 1
A46: 6.5 | B46: Responsibilities after termination or change of employment | C46: =SoA!D43 -> Yes | D46: =SoA!E43 -> Implemented | F46: ● | H46: ● | R46: =COUNTIF(E46:Q46,"●") -> 2
A47: 6.6 | B47: Confidentiality or non-disclosure agreements | C47: =SoA!D44 -> Yes | D47: =SoA!E44 -> Implemented | H47: ● | O47: ● | R47: =COUNTIF(E47:Q47,"●") -> 2
A48: 6.7 | B48: Remote working | C48: =SoA!D45 -> Yes | D48: =SoA!E45 -> Partial | E48: ● | F48: ● | K48: ● | R48: =COUNTIF(E48:Q48,"●") -> 3
A49: 6.8 | B49: Information security event reporting | C49: =SoA!D46 -> Yes | D49: =SoA!E46 -> Implemented | F49: ● | K49: ● | R49: =COUNTIF(E49:Q49,"●") -> 2
A50: 7.1 | B50: Physical security perimeters | C50: =SoA!D47 -> No | D50: =SoA!E47 -> N/A | R50: =COUNTIF(E50:Q50,"●") -> 0
A51: 7.2 | B51: Physical entry | C51: =SoA!D48 -> No | D51: =SoA!E48 -> N/A | R51: =COUNTIF(E51:Q51,"●") -> 0
A52: 7.3 | B52: Securing offices, rooms and facilities | C52: =SoA!D49 -> No | D52: =SoA!E49 -> N/A | R52: =COUNTIF(E52:Q52,"●") -> 0
A53: 7.4 | B53: Physical security monitoring | C53: =SoA!D50 -> No | D53: =SoA!E50 -> N/A | R53: =COUNTIF(E53:Q53,"●") -> 0
A54: 7.5 | B54: Protecting against physical and environmental threats | C54: =SoA!D51 -> No | D54: =SoA!E51 -> N/A | R54: =COUNTIF(E54:Q54,"●") -> 0
A55: 7.6 | B55: Working in secure areas | C55: =SoA!D52 -> No | D55: =SoA!E52 -> N/A | R55: =COUNTIF(E55:Q55,"●") -> 0
A56: 7.7 | B56: Clear desk and clear screen | C56: =SoA!D53 -> Yes | D56: =SoA!E53 -> Partial | E56: ● | F56: ● | K56: ● | R56: =COUNTIF(E56:Q56,"●") -> 3
A57: 7.8 | B57: Equipment siting and protection | C57: =SoA!D54 -> No | D57: =SoA!E54 -> N/A | R57: =COUNTIF(E57:Q57,"●") -> 0
A58: 7.9 | B58: Security of assets off-premises | C58: =SoA!D55 -> Yes | D58: =SoA!E55 -> Implemented | F58: ● | R58: =COUNTIF(E58:Q58,"●") -> 1
A59: 7.10 | B59: Storage media | C59: =SoA!D56 -> Yes | D59: =SoA!E56 -> Partial | F59: ● | H59: ● | R59: =COUNTIF(E59:Q59,"●") -> 2
A60: 7.11 | B60: Supporting utilities | C60: =SoA!D57 -> No | D60: =SoA!E57 -> N/A | R60: =COUNTIF(E60:Q60,"●") -> 0
A61: 7.12 | B61: Cabling security | C61: =SoA!D58 -> No | D61: =SoA!E58 -> N/A | R61: =COUNTIF(E61:Q61,"●") -> 0
A62: 7.13 | B62: Equipment maintenance | C62: =SoA!D59 -> Yes | D62: =SoA!E59 -> Partial | F62: ● | R62: =COUNTIF(E62:Q62,"●") -> 1
A63: 7.14 | B63: Secure disposal or re-use of equipment | C63: =SoA!D60 -> Yes | D63: =SoA!E60 -> Partial | F63: ● | O63: ● | P63: ● | R63: =COUNTIF(E63:Q63,"●") -> 3
A64: 8.1 | B64: User endpoint devices | C64: =SoA!D61 -> Yes | D64: =SoA!E61 -> Implemented | E64: ● | F64: ● | K64: ● | R64: =COUNTIF(E64:Q64,"●") -> 3
A65: 8.2 | B65: Privileged access rights | C65: =SoA!D62 -> Yes | D65: =SoA!E62 -> Partial | E65: ● | G65: ● | H65: ● | R65: =COUNTIF(E65:Q65,"●") -> 3
A66: 8.3 | B66: Information access restriction | C66: =SoA!D63 -> Yes | D66: =SoA!E63 -> Implemented | E66: ● | H66: ● | R66: =COUNTIF(E66:Q66,"●") -> 2
A67: 8.4 | B67: Access to source code | C67: =SoA!D64 -> Yes | D67: =SoA!E64 -> Implemented | H67: ● | M67: ● | N67: ● | R67: =COUNTIF(E67:Q67,"●") -> 3
A68: 8.5 | B68: Secure authentication | C68: =SoA!D65 -> Yes | D68: =SoA!E65 -> Implemented | E68: ● | K68: ● | Q68: ● | R68: =COUNTIF(E68:Q68,"●") -> 3
A69: 8.6 | B69: Capacity management | C69: =SoA!D66 -> Yes | D69: =SoA!E66 -> Partial | J69: ● | Q69: ● | R69: =COUNTIF(E69:Q69,"●") -> 2
A70: 8.7 | B70: Protection against malware | C70: =SoA!D67 -> Yes | D70: =SoA!E67 -> Implemented | K70: ● | L70: ● | R70: =COUNTIF(E70:Q70,"●") -> 2
A71: 8.8 | B71: Management of technical vulnerabilities | C71: =SoA!D68 -> Yes | D71: =SoA!E68 -> Partial | G71: ● | L71: ● | M71: ● | R71: =COUNTIF(E71:Q71,"●") -> 3
A72: 8.9 | B72: Configuration management | C72: =SoA!D69 -> Yes | D72: =SoA!E69 -> Partial | G72: ● | N72: ● | R72: =COUNTIF(E72:Q72,"●") -> 2
A73: 8.10 | B73: Information deletion | C73: =SoA!D70 -> Yes | D73: =SoA!E70 -> Partial | O73: ● | P73: ● | R73: =COUNTIF(E73:Q73,"●") -> 2
A74: 8.11 | B74: Data masking | C74: =SoA!D71 -> Yes | D74: =SoA!E71 -> Planned | E74: ● | O74: ● | R74: =COUNTIF(E74:Q74,"●") -> 2
A75: 8.12 | B75: Data leakage prevention | C75: =SoA!D72 -> Yes | D75: =SoA!E72 -> Planned | E75: ● | G75: ● | H75: ● | R75: =COUNTIF(E75:Q75,"●") -> 3
A76: 8.13 | B76: Information backup | C76: =SoA!D73 -> Yes | D76: =SoA!E73 -> Partial | J76: ● | L76: ● | P76: ● | R76: =COUNTIF(E76:Q76,"●") -> 3
A77: 8.14 | B77: Redundancy of information processing facilities | C77: =SoA!D74 -> Yes | D77: =SoA!E74 -> Implemented | I77: ● | J77: ● | L77: ● | R77: =COUNTIF(E77:Q77,"●") -> 3
A78: 8.15 | B78: Logging | C78: =SoA!D75 -> Yes | D78: =SoA!E75 -> Implemented | E78: ● | G78: ● | H78: ● | Q78: ● | R78: =COUNTIF(E78:Q78,"●") -> 4
A79: 8.16 | B79: Monitoring activities | C79: =SoA!D76 -> Yes | D79: =SoA!E76 -> Partial | E79: ● | G79: ● | H79: ● | K79: ● | R79: =COUNTIF(E79:Q79,"●") -> 4
A80: 8.17 | B80: Clock synchronization | C80: =SoA!D77 -> Yes | D80: =SoA!E77 -> Implemented | E80: ● | R80: =COUNTIF(E80:Q80,"●") -> 1
A81: 8.18 | B81: Use of privileged utility programs | C81: =SoA!D78 -> Yes | D81: =SoA!E78 -> Partial | E81: ● | H81: ● | R81: =COUNTIF(E81:Q81,"●") -> 2
A82: 8.19 | B82: Installation of software on operational systems | C82: =SoA!D79 -> Yes | D82: =SoA!E79 -> Implemented | G82: ● | M82: ● | N82: ● | R82: =COUNTIF(E82:Q82,"●") -> 3
A83: 8.20 | B83: Networks security | C83: =SoA!D80 -> Yes | D83: =SoA!E80 -> Implemented | E83: ● | G83: ● | Q83: ● | R83: =COUNTIF(E83:Q83,"●") -> 3
A84: 8.21 | B84: Security of network services | C84: =SoA!D81 -> Yes | D84: =SoA!E81 -> Partial | I84: ● | Q84: ● | R84: =COUNTIF(E84:Q84,"●") -> 2
A85: 8.22 | B85: Segregation of networks | C85: =SoA!D82 -> Yes | D85: =SoA!E82 -> Implemented | E85: ● | G85: ● | L85: ● | R85: =COUNTIF(E85:Q85,"●") -> 3
A86: 8.23 | B86: Web filtering | C86: =SoA!D83 -> Yes | D86: =SoA!E83 -> Planned | K86: ● | R86: =COUNTIF(E86:Q86,"●") -> 1
A87: 8.24 | B87: Use of cryptography | C87: =SoA!D84 -> Yes | D87: =SoA!E84 -> Implemented | E87: ● | F87: ● | I87: ● | R87: =COUNTIF(E87:Q87,"●") -> 3
A88: 8.25 | B88: Secure development life cycle | C88: =SoA!D85 -> Yes | D88: =SoA!E85 -> Implemented | G88: ● | M88: ● | Q88: ● | R88: =COUNTIF(E88:Q88,"●") -> 3
A89: 8.26 | B89: Application security requirements | C89: =SoA!D86 -> Yes | D89: =SoA!E86 -> Partial | E89: ● | Q89: ● | R89: =COUNTIF(E89:Q89,"●") -> 2
A90: 8.27 | B90: Secure system architecture and engineering principles | C90: =SoA!D87 -> Yes | D90: =SoA!E87 -> Partial | G90: ● | Q90: ● | R90: =COUNTIF(E90:Q90,"●") -> 2
A91: 8.28 | B91: Secure coding | C91: =SoA!D88 -> Yes | D91: =SoA!E88 -> Partial | M91: ● | N91: ● | Q91: ● | R91: =COUNTIF(E91:Q91,"●") -> 3
A92: 8.29 | B92: Security testing in development and acceptance | C92: =SoA!D89 -> Yes | D92: =SoA!E89 -> Partial | M92: ● | N92: ● | Q92: ● | R92: =COUNTIF(E92:Q92,"●") -> 3
A93: 8.30 | B93: Outsourced development | C93: =SoA!D90 -> No | D93: =SoA!E90 -> N/A | R93: =COUNTIF(E93:Q93,"●") -> 0
A94: 8.31 | B94: Separation of development, test and production environments | C94: =SoA!D91 -> Yes | D94: =SoA!E91 -> Implemented | E94: ● | G94: ● | R94: =COUNTIF(E94:Q94,"●") -> 2
A95: 8.32 | B95: Change management | C95: =SoA!D92 -> Yes | D95: =SoA!E92 -> Implemented | G95: ● | R95: =COUNTIF(E95:Q95,"●") -> 1
A96: 8.33 | B96: Test information | C96: =SoA!D93 -> Yes | D96: =SoA!E93 -> Planned | E96: ● | O96: ● | R96: =COUNTIF(E96:Q96,"●") -> 2
A97: 8.34 | B97: Protection of information systems during audit testing | C97: =SoA!D94 -> Yes | D97: =SoA!E94 -> Planned | J97: ● | R97: =COUNTIF(E97:Q97,"●") -> 1
A99: Controls with no risk marked (applicable only): | D99: =COUNTIFS(C5:C97,"Yes",R5:R97,0) -> 1
A100: Expected: 1 (5.35, driven by ISO/IEC 27001 clause 9.2 rather than a risk). Reserve 'Excluded' controls rely on inherited or alternative measures; see Exclusions.

Sheet Evidence Index
A1: Evidence Reference Index
A2: Owners are proposed roles and systems of record are indicative. 'Controls citing' counts SoA rows that reference the ID.
A4: ID | B4: Evidence artefact | C4: Proposed owner | D4: System of record (indicative) | E4: Cadence | F4: Controls citing (live) | G4: Note
A5: EV-01 | B5: Information security policy, approved by management | C5: ISMS Manager | D5: Policy repository | E5: Annual | F5: =COUNTIF(SoA!$G$2:$G$94,"*"&A5&"*") -> 1
A6: EV-02 | B6: ISMS scope statement and context register (incl. climate-change consideration) | C6: ISMS Manager | D6: Policy repository | E6: Annual | F6: =COUNTIF(SoA!$G$2:$G$94,"*"&A6&"*") -> 0 | G6: Clause 4 evidence
A7: EV-03 | B7: Roles and responsibilities matrix, appointment records | C7: ISMS Manager | D7: Policy repository | E7: On change | F7: =COUNTIF(SoA!$G$2:$G$94,"*"&A7&"*") -> 2
A8: EV-04 | B8: Management review minutes and ISMS KPI pack | C8: Executive sponsor | D8: Document store | E8: Quarterly | F8: =COUNTIF(SoA!$G$2:$G$94,"*"&A8&"*") -> 1
A9: EV-05 | B9: Risk assessment methodology (criteria, matrix) and risk register | C9: Risk Owner | D9: Risk register | E9: Semi-annual | F9: =COUNTIF(SoA!$G$2:$G$94,"*"&A9&"*") -> 0 | G9: Clause 6.1.2 evidence
A10: EV-06 | B10: Risk treatment plan | C10: Risk Owner | D10: Risk register | E10: Semi-annual | F10: =COUNTIF(SoA!$G$2:$G$94,"*"&A10&"*") -> 0 | G10: Clause 6.1.3 evidence
A11: EV-07 | B11: Information asset register with owners and classification | C11: IT Operations Lead | D11: Asset inventory | E11: Quarterly | F11: =COUNTIF(SoA!$G$2:$G$94,"*"&A11&"*") -> 1
A12: EV-08 | B12: Acceptable use policy and signed acknowledgements | C12: Head of People | D12: HR system | E12: Onboarding and annual | F12: =COUNTIF(SoA!$G$2:$G$94,"*"&A12&"*") -> 1
A13: EV-09 | B13: Classification and handling standard; labelling and transfer rules | C13: ISMS Manager | D13: Policy repository | E13: Annual | F13: =COUNTIF(SoA!$G$2:$G$94,"*"&A13&"*") -> 3
A14: EV-10 | B14: Access control policy | C14: Head of Engineering | D14: Policy repository | E14: Annual | F14: =COUNTIF(SoA!$G$2:$G$94,"*"&A14&"*") -> 1
A15: EV-11 | B15: Identity and access configuration exports and quarterly access review records | C15: Cloud Platform Lead | D15: Identity provider, AWS IAM | E15: Quarterly | F15: =COUNTIF(SoA!$G$2:$G$94,"*"&A15&"*") -> 7
A16: EV-12 | B16: Supplier register, due-diligence files and AWS assurance reviews (certificates, SOC reports) | C16: Procurement and ISMS Manager | D16: Supplier register, AWS Artifact | E16: Annual per supplier | F16: =COUNTIF(SoA!$G$2:$G$94,"*"&A16&"*") -> 7
A17: EV-13 | B17: Supplier contracts, DPAs, NDAs and security addenda | C17: Legal | D17: Contract repository | E17: On signature and renewal | F17: =COUNTIF(SoA!$G$2:$G$94,"*"&A17&"*") -> 2
A18: EV-14 | B18: Cloud security standard and shared-responsibility matrix | C18: Cloud Platform Lead | D18: Policy repository | E18: Annual | F18: =COUNTIF(SoA!$G$2:$G$94,"*"&A18&"*") -> 2
A19: EV-15 | B19: Incident response plan, playbooks, incident log, post-incident reviews, tabletop reports | C19: Security Lead | D19: Ticketing system | E19: Per incident; tabletop annually | F19: =COUNTIF(SoA!$G$2:$G$94,"*"&A19&"*") -> 5
A20: EV-16 | B20: Business impact analysis, continuity and DR plans, DR test reports | C20: Head of Operations | D20: Document store | E20: Annual test | F20: =COUNTIF(SoA!$G$2:$G$94,"*"&A20&"*") -> 3
A21: EV-17 | B21: Legal and contractual requirements register | C21: Legal | D21: Document store | E21: Semi-annual | F21: =COUNTIF(SoA!$G$2:$G$94,"*"&A21&"*") -> 1
A22: EV-18 | B22: Record of processing, DPIAs, DSAR procedure and log | C22: Data Protection Lead | D22: Privacy register | E22: Semi-annual | F22: =COUNTIF(SoA!$G$2:$G$94,"*"&A22&"*") -> 1
... A54: EV-50 | B54: Event reporting channel and reporting statistics | C54: Security Lead | D54: Ticketing, chat | E54: Monthly | F54: =COUNTIF(SoA!$G$2:$G$94,"*"&A54&"*") -> 1

Sheet Actions
A1: Priority Remediation Actions
A2: Owners are proposed roles; dates are proposals for management approval. Update Status as work progresses.
A4: ID | B4: Control | C4: Action | D4: Owner | E4: Due | F4: Risk addressed | G4: Status | H4: Days to due (live)
A5: A-01 | B5: Baseline | C5: Confirm whether any staff access company data from personal phones; if so add mobile rule to 8.1 and 6.7 | D5: IT Operations Lead | E5: 46346 | F5: R-002, R-007 | G5: Not started | H5: =E5-DATE(2026,10,26) -> 25
A6: A-02 | B6: Method | C6: Publish risk scoring matrix and likelihood and impact criteria | D6: Risk Owner | E6: 46346 | F6: All | G6: Not started | H6: =E6-DATE(2026,10,26) -> 25
A7: A-03 | B7: ED-01 to ED-04 | C7: Assemble non-applicability dossier (EV-43) including contributor-to-roster reconciliation | D7: ISMS Manager | E7: 46346 | F7: All exclusions | G7: Not started | H7: =E7-DATE(2026,10,26) -> 25
A8: A-04 | B8: 5.22 | C8: Complete and sign off the annual AWS assurance review; schedule reviews for other suppliers | D8: ISMS Manager | E8: 46360 | F8: R-005 | G8: Not started | H8: =E8-DATE(2026,10,26) -> 39
A9: A-05 | B9: 8.34 | C9: Write audit and penetration test protocol with read-only access rules | D9: Security Lead | E9: 46360 | F9: R-001, R-006 | G9: Not started | H9: =E9-DATE(2026,10,26) -> 39
A10: A-06 | B10: 8.23 | C10: Deploy DNS and web filtering to all laptops through MDM | D10: IT Operations Lead | E10: 46367 | F10: R-007 | G10: Not started | H10: =E10-DATE(2026,10,26) -> 46
A11: A-07 | B11: 5.13 | C11: Apply classification tags to cloud data stores and standard document footers | D11: ISMS Manager | E11: 46374 | F11: R-001, R-011 | G11: Not started | H11: =E11-DATE(2026,10,26) -> 53
A12: A-08 | B12: 5.28 | C12: Approve evidence-collection and forensic-readiness procedure; confirm log retention | D12: Security Lead | E12: 46374 | F12: R-001, R-004 | G12: Not started | H12: =E12-DATE(2026,10,26) -> 53
A13: A-09 | B13: 5.18 | C13: Extend quarterly access reviews to all SaaS applications | D13: Cloud Platform Lead | E13: 46374 | F13: R-001, R-004 | G13: Not started | H13: =E13-DATE(2026,10,26) -> 53
A14: A-10 | B14: 8.9 | C14: Enable configuration drift detection and exception process for infrastructure-as-code | D14: Cloud Platform Lead | E14: 46402 | F14: R-003, R-010 | G14: Not started | H14: =E14-DATE(2026,10,26) -> 81
A15: A-11 | B15: 8.16 | C15: Tune alerts and define out-of-hours escalation | D15: Security Lead | E15: 46402 | F15: R-003, R-007 | G15: Not started | H15: =E15-DATE(2026,10,26) -> 81
A16: A-12 | B16: 8.8 | C16: Set remediation SLAs and monthly vulnerability reporting | D16: Security Lead | E16: 46402 | F16: R-003, R-008, R-009 | G16: Not started | H16: =E16-DATE(2026,10,26) -> 81
... A24: A-20 | B24: 5.35 | C24: Complete first independent internal audit of the ISMS | D24: ISMS Manager | E24: 46430 | F24: Clause 9.2 | G24: Not started | H24: =E24-DATE(2026,10,26) -> 109
A26: Days to due is measured from the baseline date 26 Oct 2026 (fixed).

Sheet Additional Controls
A1: Controls Beyond Annex A
A2: Clause 6.1.3 b): controls necessary for a multi-tenant, EU-hosted SaaS provider. They do not change the 93-control count.
A4: Ref | B4: Additional control | C4: Risks | D4: Related Annex A | E4: Status | F4: Evidence Ref
A5: C-01 | B5: Logical tenant isolation for customer data in the multi-tenant platform | C5: R-001 R-013 | D5: 8.3, 8.22, 8.26 | E5: Partial | F5: EV-25, EV-32
A6: C-02 | B6: EU data residency enforcement and sub-processor transparency | C6: R-011 | D6: 5.20, 5.31, 8.9 | E6: Partial | F6: EV-13, EV-37
A7: C-03 | B7: Customer assurance handling: security questionnaires, audit-rights requests, shared-responsibility statement | C7: R-005 R-011 | D7: 5.19, 5.31 | E7: Planned | F7: EV-12, EV-17
